{"cameraMode":{"drawMode":0,"name":"Shaded","section":"Shading Mode"},"sceneLighting":false,"audioPlay":false,"sceneViewState":{"m_AlwaysRefresh":false,"showFog":true,"showSkybox":false,"showFlares":true,"showImageEffects":true,"showParticleSystems":true,"showVisualEffectGraphs":true,"m_FxEnabled":true},"in2DMode":false,"pivot":{"x":-2.499998092651367,"y":1.5,"z":-1.9959261417388917},"rotation":{"x":0.11376814544200897,"y":0.5010188221931458,"z":-0.06682834029197693,"w":0.8555052876472473},"size":4.186223983764648,"orthographic":false}